skein_hash.cp36-win_amd64.pyd
coin_skein_hash-1.1.dist-info/LICENSE
coin_skein_hash-1.1.dist-info/METADATA
coin_skein_hash-1.1.dist-info/WHEEL
coin_skein_hash-1.1.dist-info/top_level.txt
coin_skein_hash-1.1.dist-info/RECORD
