Metadata-Version: 2.1
Name: coin-skein-hash
Version: 1.1
Summary: Binding for CHIPO skein proof of work hashing.
Home-page: https://github.com/CHIPO-Project/skein-hash-python
Author: nakkie
Author-email: nakkie@linux.jpn.com
Maintainer: nakkie
Maintainer-email: nakkie@linux.jpn.com
License: MIT
Download-URL: https://github.com/CHIPO-Project/skein-hash-python/archive/v1.0.tar.gz
Platform: UNKNOWN
